<mujoco><body name="cube_fillet_45_normal_4" pos="0 0 0">
    <inertial diaginertia="0.0004664990952182619 0.0004664990952182619 0.0004664990952182619" mass="0.1854390670553935" pos="0 0 0" quat="1 0 0 0"/>
    <freejoint name="cube_fillet_45_normal_4"/>
    <geom mesh="cube_fillet_45_normal_4" name="cube_fillet_45_normal_4_geom" type="mesh"/>
  </body>
  <body name="cuboid_311_fillet_45_normal_5" pos="0 0 0">
    <inertial diaginertia="2.8011666666666658e-05 0.0001400583333333333 0.0001400583333333333" mass="0.0343" pos="0 0 0" quat="1 0 0 0"/>
    <freejoint name="cuboid_311_fillet_45_normal_5"/>
    <geom mesh="cuboid_311_fillet_45_normal_5" name="cuboid_311_fillet_45_normal_5_geom" type="mesh"/>
  </body>
  <body name="sphere_normal_83" pos="0 0 0">
    <inertial diaginertia="6.506963713669752e-05 6.506963713669752e-05 6.506963713669752e-05" mass="0.07727286790148581" pos="0 0 0" quat="1 0 0 0"/>
    <freejoint name="sphere_normal_83"/>
    <geom mesh="sphere_normal_83" name="sphere_normal_83_geom" type="mesh"/>
  </body>
  <body name="cylinder_21_fillet_35_normal_15" pos="0 0 0">
    <inertial diaginertia="2.3893333333333344e-05 2.3893333333333344e-05 5.120000000000004e-06" mass="0.006400000000000002" pos="0 0 0" quat="1 0 0 0"/>
    <freejoint name="cylinder_21_fillet_35_normal_15"/>
    <geom mesh="cylinder_21_fillet_35_normal_15" name="cylinder_21_fillet_35_normal_15_geom" type="mesh"/>
  </body>
  <body name="cube_fillet_45_normal_15" pos="0 0 0">
    <inertial diaginertia="1.2959999999999998e-05 1.2959999999999998e-05 1.2959999999999998e-05" mass="0.021599999999999998" pos="0 0 0" quat="1 0 0 0"/>
    <freejoint name="cube_fillet_45_normal_15"/>
    <geom mesh="cube_fillet_45_normal_15" name="cube_fillet_45_normal_15_geom" type="mesh"/>
  </body>
  <body name="cuboid_311_fillet_35_normal_8" pos="0 0 0">
    <inertial diaginertia="1.5894571940104164e-05 7.947285970052082e-05 7.947285970052082e-05" mass="0.0244140625" pos="0 0 0" quat="1 0 0 0"/>
    <freejoint name="cuboid_311_fillet_35_normal_8"/>
    <geom mesh="cuboid_311_fillet_35_normal_8" name="cuboid_311_fillet_35_normal_8_geom" type="mesh"/>
  </body>
  <body name="cylinder_21_fillet_35_normal_1" pos="0 0 0">
    <inertial diaginertia="0.0006943725000000002 0.0006943725000000002 0.00029524500000000013" mass="0.07290000000000002" pos="0 0 0" quat="1 0 0 0"/>
    <freejoint name="cylinder_21_fillet_35_normal_1"/>
    <geom mesh="cylinder_21_fillet_35_normal_1" name="cylinder_21_fillet_35_normal_1_geom" type="mesh"/>
  </body>
  <body name="cuboid_321_fillet_25_normal_9" pos="0 0 0">
    <inertial diaginertia="4.266666666666669e-06 1.1093333333333338e-05 8.533333333333335e-06" mass="0.006400000000000002" pos="0 0 0" quat="0.7071 0.7071 0 0"/>
    <freejoint name="cuboid_321_fillet_25_normal_9"/>
    <geom mesh="cuboid_321_fillet_25_normal_9" name="cuboid_321_fillet_25_normal_9_geom" type="mesh"/>
  </body>
  <body name="sphere_normal_24" pos="0 0 0">
    <inertial diaginertia="0.0003235546849964467 0.0003235546849964467 0.0003235546849964467" mass="0.202287299002646" pos="0 0 0" quat="1 0 0 0"/>
    <freejoint name="sphere_normal_24"/>
    <geom mesh="sphere_normal_24" name="sphere_normal_24_geom" type="mesh"/>
  </body>
  <body name="cylinder_14_fillet_15_normal_12" pos="0 0 0">
    <inertial diaginertia="0.00065716477938531 0.00065716477938531 1.6169052731469775e-05" mass="0.029313301749271135" pos="0 0 0" quat="0.683 0.683 0.183 0.183"/>
    <freejoint name="cylinder_14_fillet_15_normal_12"/>
    <geom mesh="cylinder_14_fillet_15_normal_12" name="cylinder_14_fillet_15_normal_12_geom" type="mesh"/>
  </body>
  <body name="cylinder_11_fillet_25_normal_14" pos="0 0 0">
    <inertial diaginertia="0.0002785034179687501 0.0002785034179687501 2.966308593750001e-05" mass="0.0421875" pos="0 0 0" quat="1 0 0 0"/>
    <freejoint name="cylinder_11_fillet_25_normal_14"/>
    <geom mesh="cylinder_11_fillet_25_normal_14" name="cylinder_11_fillet_25_normal_14_geom" type="mesh"/>
  </body>
  <body name="cylinder_12_fillet_25_sideways_5" pos="0 0 0">
    <inertial diaginertia="0.0019374162860712795 0.0019374162860712795 0.00014390712441244714" mass="0.10881865889212826" pos="0 0 0" quat="0.683 0.683 0.183 0.183"/>
    <freejoint name="cylinder_12_fillet_25_sideways_5"/>
    <geom mesh="cylinder_12_fillet_25_sideways_5" name="cylinder_12_fillet_25_sideways_5_geom" type="mesh"/>
  </body>
  <body name="cuboid_311_fillet_35_thinner_4" pos="0 0 0">
    <inertial diaginertia="5.5256328124999984e-05 0.0007088381640624997 0.0007088381640624997" mass="0.06307499999999999" pos="0 0 0" quat="1 0 0 0"/>
    <freejoint name="cuboid_311_fillet_35_thinner_4"/>
    <geom mesh="cuboid_311_fillet_35_thinner_4" name="cuboid_311_fillet_35_thinner_4_geom" type="mesh"/>
  </body>
  <body name="cuboid_311_fillet_25_normal_7" pos="0 0 0">
    <inertial diaginertia="1.933817708333334e-05 9.669088541666669e-05 9.669088541666669e-05" mass="0.027462500000000004" pos="0 0 0" quat="1 0 0 0"/>
    <freejoint name="cuboid_311_fillet_25_normal_7"/>
    <geom mesh="cuboid_311_fillet_25_normal_7" name="cuboid_311_fillet_25_normal_7_geom" type="mesh"/>
  </body>
  <body name="cuboid_321_fillet_45_normal_3" pos="0 0 0">
    <inertial diaginertia="1.0075272623697915e-05 2.6195708821614575e-05 2.015054524739583e-05" mass="0.0107171875" pos="0 0 0" quat="0.7071 0.7071 0 0"/>
    <freejoint name="cuboid_321_fillet_45_normal_3"/>
    <geom mesh="cuboid_321_fillet_45_normal_3" name="cuboid_321_fillet_45_normal_3_geom" type="mesh"/>
  </body>
  <body name="cylinder_14_fillet_5_normal_2" pos="0 0 0">
    <inertial diaginertia="0.002018752079726592 0.002018752079726592 6.543278294339782e-05" mass="0.06781585276967929" pos="0 0 0" quat="0.683 0.683 0.183 0.183"/>
    <freejoint name="cylinder_14_fillet_5_normal_2"/>
    <geom mesh="cylinder_14_fillet_5_normal_2" name="cylinder_14_fillet_5_normal_2_geom" type="mesh"/>
  </body>
  <body name="cuboid_221_fillet_35_normal_8" pos="0 0 0">
    <inertial diaginertia="6.67850176493327e-06 1.0685602823893232e-05 6.67850176493327e-06" mass="0.008374023437500001" pos="0 0 0" quat="0.7071 0.7071 0 0"/>
    <freejoint name="cuboid_221_fillet_35_normal_8"/>
    <geom mesh="cuboid_221_fillet_35_normal_8" name="cuboid_221_fillet_35_normal_8_geom" type="mesh"/>
  </body>
  <body name="cuboid_321_fillet_15_normal_9" pos="0 0 0">
    <inertial diaginertia="4.266666666666669e-06 1.1093333333333338e-05 8.533333333333335e-06" mass="0.006400000000000002" pos="0 0 0" quat="0.7071 0.7071 0 0"/>
    <freejoint name="cuboid_321_fillet_15_normal_9"/>
    <geom mesh="cuboid_321_fillet_15_normal_9" name="cuboid_321_fillet_15_normal_9_geom" type="mesh"/>
  </body>
  <body name="sphere_normal_80" pos="0 0 0">
    <inertial diaginertia="7.15716475666211e-05 7.15716475666211e-05 7.15716475666211e-05" mass="0.08181719926725012" pos="0 0 0" quat="1 0 0 0"/>
    <freejoint name="sphere_normal_80"/>
    <geom mesh="sphere_normal_80" name="sphere_normal_80_geom" type="mesh"/>
  </body>
  <body name="cuboid_211_fillet_35_normal_4" pos="0 0 0">
    <inertial diaginertia="5.04779328918457e-05 0.00012619483222961426 0.00012619483222961426" mass="0.0488373046875" pos="0 0 0" quat="1 0 0 0"/>
    <freejoint name="cuboid_211_fillet_35_normal_4"/>
    <geom mesh="cuboid_211_fillet_35_normal_4" name="cuboid_211_fillet_35_normal_4_geom" type="mesh"/>
  </body>
  <body name="ground" pos="0 0 0">
    <geom name="ground_geom" size="1 1 1" type="plane"/>
  </body>
</mujoco>