<mujoco><mesh file="models/cylinder_13/cylinder_13_fillet_15.STL" name="cylinder_13_fillet_15_sideways_9" refquat="0.683 -0.683 -0.183 -0.183" scale="0.7285714285714285 0.7285714285714285 0.7285714285714285"/>
  <mesh file="models/cylinder_14/cylinder_14_fillet_5.STL" name="cylinder_14_fillet_5_normal_7" refquat="0.683 -0.683 -0.183 -0.183" scale="0.7714285714285715 0.7714285714285715 0.7714285714285715"/>
  <mesh file="models/cube/cube_fillet_45.STL" name="cube_fillet_45_normal_12" refquat="1 0 0 0" scale="0.7714285714285714 0.7714285714285714 0.7714285714285714"/>
  <mesh file="models/sphere/sphere.STL" name="sphere_normal_107" refquat="1 0 0 0" scale="0.776470588235294 0.776470588235294 0.776470588235294"/>
  <mesh file="models/cube/cube_fillet_15.STL" name="cube_fillet_15_normal_10" refquat="1 0 0 0" scale="0.8857142857142857 0.8857142857142857 0.8857142857142857"/>
  <mesh file="models/sphere/sphere.STL" name="sphere_normal_67" refquat="1 0 0 0" scale="1.011764705882353 1.011764705882353 1.011764705882353"/>
  <mesh file="models/cylinder_12/cylinder_12_fillet_25.STL" name="cylinder_12_fillet_25_sideways_12" refquat="0.683 -0.683 -0.183 -0.183" scale="0.7285714285714285 0.7285714285714285 0.7285714285714285"/>
  <mesh file="models/cylinder_14/cylinder_14_fillet_5.STL" name="cylinder_14_fillet_5_normal_12" refquat="0.683 -0.683 -0.183 -0.183" scale="0.6642857142857143 0.6642857142857143 0.6642857142857143"/>
  <mesh file="models/cylinder_12/cylinder_12_fillet_25.STL" name="cylinder_12_fillet_25_upright_14" refquat="0 -0.01 0 0" scale="0.6071428571428571 0.6071428571428571 0.6071428571428571"/>
  <mesh file="models/cube/cube_fillet_35.STL" name="cube_fillet_35_normal_1" refquat="1 0 0 0" scale="1.4 1.4 1.4"/>
  <mesh file="models/cylinder_12/cylinder_12_fillet_5.STL" name="cylinder_12_fillet_5_upright_6" refquat="0 -0.01 0 0" scale="0.6642857142857143 0.6642857142857143 0.6642857142857143"/>
  <mesh file="models/sphere/sphere.STL" name="sphere_normal_13" refquat="1 0 0 0" scale="1.3294117647058823 1.3294117647058823 1.3294117647058823"/>
  <mesh file="models/cylinder_11/cylinder_11_fillet_35.STL" name="cylinder_11_fillet_35_normal_7" refquat="1 0 0 0" scale="1.0999999999999999 1.0999999999999999 1.0999999999999999"/>
  <mesh file="models/sphere/sphere.STL" name="sphere_normal_4" refquat="1 0 0 0" scale="1.3823529411764706 1.3823529411764706 1.3823529411764706"/>
  <mesh file="models/cube/cube_fillet_15.STL" name="cube_fillet_15_normal_2" refquat="1 0 0 0" scale="1.3428571428571427 1.3428571428571427 1.3428571428571427"/>
  <mesh file="models/cylinder_12/cylinder_12_fillet_25.STL" name="cylinder_12_fillet_25_upright_12" refquat="0 -0.01 0 0" scale="0.6214285714285714 0.6214285714285714 0.6214285714285714"/>
  <mesh file="models/cylinder_12/cylinder_12_fillet_25.STL" name="cylinder_12_fillet_25_sideways_8" refquat="0.683 -0.683 -0.183 -0.183" scale="0.8999999999999999 0.8999999999999999 0.8999999999999999"/>
  <mesh file="models/cylinder_14/cylinder_14_fillet_5.STL" name="cylinder_14_fillet_5_normal_9" refquat="0.683 -0.683 -0.183 -0.183" scale="0.7285714285714285 0.7285714285714285 0.7285714285714285"/>
  <mesh file="models/cylinder_21/cylinder_21_fillet_25.STL" name="cylinder_21_fillet_25_normal_7" refquat="1 0 0 0" scale="0.6857142857142857 0.6857142857142857 0.6857142857142857"/>
  <mesh file="models/cube/cube_fillet_35.STL" name="cube_fillet_35_normal_13" refquat="1 0 0 0" scale="0.7142857142857142 0.7142857142857142 0.7142857142857142"/>
  </mujoco>