<mujoco><body name="cuboid_311_fillet_35_thinner_0" pos="0 0 0">
    <inertial pos="0 0 0" quat="1 0 0 0" mass="0.1296" diaginertia="0.000078 0.001439 0.001439"/>
    <freejoint name="cuboid_311_fillet_35_thinner_0"/>
    <geom name="cuboid_311_fillet_35_thinner_0_geom" type="mesh" mesh="cuboid_311_fillet_35_thinner_0"/>
  </body><body name="cylinder_14_fillet_25_normal_13" pos="0 0 0">
    <inertial pos="0 0 0" quat="0.5 0.5 0.5 0.5" mass="0.2130497848581515" diaginertia="0.002295 0.002295 0.000206"/>
    <freejoint name="cylinder_14_fillet_25_normal_13"/>
    <geom name="cylinder_14_fillet_25_normal_13_geom" type="mesh" mesh="cylinder_14_fillet_25_normal_13"/>
  </body><body name="cuboid_321_fillet_25_normal_5" pos="0 0 0">
    <inertial pos="0 0 0" quat="0.7071 0.7071 0 0" mass="0.05935898437500003" diaginertia="0.000053 0.000138 0.000106"/>
    <freejoint name="cuboid_321_fillet_25_normal_5"/>
    <geom name="cuboid_321_fillet_25_normal_5_geom" type="mesh" mesh="cuboid_321_fillet_25_normal_5"/>
  </body><body name="cylinder_12_fillet_25_sideways_3" pos="0 0 0">
    <inertial pos="0 0 0" quat="0.5 0.5 0.5 0.5" mass="0.06074860161681335" diaginertia="0.000128 0.000128 0.000040"/>
    <freejoint name="cylinder_12_fillet_25_sideways_3"/>
    <geom name="cylinder_12_fillet_25_sideways_3_geom" type="mesh" mesh="cylinder_12_fillet_25_sideways_3"/>
  </body><body name="cylinder_21_fillet_15_normal_0" pos="0 0 0">
    <inertial pos="0 0 0" quat="1 0 0 0" mass="0.020106192982974686" diaginertia="0.000011 0.000011 0.000016"/>
    <freejoint name="cylinder_21_fillet_15_normal_0"/>
    <geom name="cylinder_21_fillet_15_normal_0_geom" type="mesh" mesh="cylinder_21_fillet_15_normal_0"/>
  </body><body name="cuboid_221_fillet_25_normal_2" pos="0 0 0">
    <inertial pos="0 0 0" quat="0.7071 0.7071 0 0" mass="0.042868750000000004" diaginertia="0.000040 0.000064 0.000040"/>
    <freejoint name="cuboid_221_fillet_25_normal_2"/>
    <geom name="cuboid_221_fillet_25_normal_2_geom" type="mesh" mesh="cuboid_221_fillet_25_normal_2"/>
  </body><body name="cylinder_12_fillet_15_upright_13" pos="0 0 0">
    <inertial pos="0 0 0" quat="0 0.01 0 0" mass="0.05224575058181045" diaginertia="0.000099 0.000099 0.000031"/>
    <freejoint name="cylinder_12_fillet_15_upright_13"/>
    <geom name="cylinder_12_fillet_15_upright_13_geom" type="mesh" mesh="cylinder_12_fillet_15_upright_13"/>
  </body><body name="cylinder_14_fillet_5_normal_5" pos="0 0 0">
    <inertial pos="0 0 0" quat="0.5 0.5 0.5 0.5" mass="0.11108907471521585" diaginertia="0.000775 0.000775 0.000069"/>
    <freejoint name="cylinder_14_fillet_5_normal_5"/>
    <geom name="cylinder_14_fillet_5_normal_5_geom" type="mesh" mesh="cylinder_14_fillet_5_normal_5"/>
  </body><body name="cuboid_321_fillet_15_normal_1" pos="0 0 0">
    <inertial pos="0 0 0" quat="0.7071 0.7071 0 0" mass="0.042113671875000015" diaginertia="0.000030 0.000078 0.000060"/>
    <freejoint name="cuboid_321_fillet_15_normal_1"/>
    <geom name="cuboid_321_fillet_15_normal_1_geom" type="mesh" mesh="cuboid_321_fillet_15_normal_1"/>
  </body><body name="cube_fillet_5_normal_13" pos="0 0 0">
    <inertial pos="0 0 0" quat="1 0 0 0" mass="0.24215276967930044" diaginertia="0.000728 0.000728 0.000728"/>
    <freejoint name="cube_fillet_5_normal_13"/>
    <geom name="cube_fillet_5_normal_13_geom" type="mesh" mesh="cube_fillet_5_normal_13"/>
  </body><body name="cuboid_311_fillet_25_thinner_7" pos="0 0 0">
    <inertial pos="0 0 0" quat="1 0 0 0" mass="0.21622500000000006" diaginertia="0.000216 0.002443 0.002443"/>
    <freejoint name="cuboid_311_fillet_25_thinner_7"/>
    <geom name="cuboid_311_fillet_25_thinner_7_geom" type="mesh" mesh="cuboid_311_fillet_25_thinner_7"/>
  </body><body name="cuboid_211_fillet_45_normal_5" pos="0 0 0">
    <inertial pos="0 0 0" quat="1 0 0 0" mass="0.09767460937500001" diaginertia="0.000101 0.000252 0.000252"/>
    <freejoint name="cuboid_211_fillet_45_normal_5"/>
    <geom name="cuboid_211_fillet_45_normal_5_geom" type="mesh" mesh="cuboid_211_fillet_45_normal_5"/>
  </body><body name="cylinder_11_fillet_45_normal_3" pos="0 0 0">
    <inertial pos="0 0 0" quat="1 0 0 0" mass="0.04823326470964581" diaginertia="0.000051 0.000051 0.000044"/>
    <freejoint name="cylinder_11_fillet_45_normal_3"/>
    <geom name="cylinder_11_fillet_45_normal_3_geom" type="mesh" mesh="cylinder_11_fillet_45_normal_3"/>
  </body><body name="cylinder_12_fillet_25_upright_3" pos="0 0 0">
    <inertial pos="0 0 0" quat="0 0.01 0 0" mass="0.03769584889152405" diaginertia="0.000058 0.000058 0.000018"/>
    <freejoint name="cylinder_12_fillet_25_upright_3"/>
    <geom name="cylinder_12_fillet_25_upright_3_geom" type="mesh" mesh="cylinder_12_fillet_25_upright_3"/>
  </body><body name="cube_fillet_5_normal_8" pos="0 0 0">
    <inertial pos="0 0 0" quat="1 0 0 0" mass="0.11814110787172012" diaginertia="0.000220 0.000220 0.000220"/>
    <freejoint name="cube_fillet_5_normal_8"/>
    <geom name="cube_fillet_5_normal_8_geom" type="mesh" mesh="cube_fillet_5_normal_8"/>
  </body><body name="cuboid_311_fillet_5_thinner_2" pos="0 0 0">
    <inertial pos="0 0 0" quat="1 0 0 0" mass="0.1521" diaginertia="0.000107 0.001696 0.001696"/>
    <freejoint name="cuboid_311_fillet_5_thinner_2"/>
    <geom name="cuboid_311_fillet_5_thinner_2_geom" type="mesh" mesh="cuboid_311_fillet_5_thinner_2"/>
  </body><body name="cuboid_211_fillet_15_upright_0" pos="0 0 0">
    <inertial pos="0 0 0" quat="0.707 0 0.707 0" mass="0.025000000000000005" diaginertia="0.000010 0.000026 0.000026"/>
    <freejoint name="cuboid_211_fillet_15_upright_0"/>
    <geom name="cuboid_211_fillet_15_upright_0_geom" type="mesh" mesh="cuboid_211_fillet_15_upright_0"/>
  </body><body name="sphere_normal_91" pos="0 0 0">
    <inertial pos="0 0 0" quat="1 0 0 0" mass="0.0986983159132067" diaginertia="0.000151 0.000151 0.000151"/>
    <freejoint name="sphere_normal_91"/>
    <geom name="sphere_normal_91_geom" type="mesh" mesh="sphere_normal_91"/>
  </body><body name="sphere_normal_80" pos="0 0 0">
    <inertial pos="0 0 0" quat="1 0 0 0" mass="0.08398681024590224" diaginertia="0.000115 0.000115 0.000115"/>
    <freejoint name="sphere_normal_80"/>
    <geom name="sphere_normal_80_geom" type="mesh" mesh="sphere_normal_80"/>
  </body><body name="cuboid_311_fillet_45_thinner_0" pos="0 0 0">
    <inertial pos="0 0 0" quat="1 0 0 0" mass="0.1296" diaginertia="0.000078 0.001439 0.001439"/>
    <freejoint name="cuboid_311_fillet_45_thinner_0"/>
    <geom name="cuboid_311_fillet_45_thinner_0_geom" type="mesh" mesh="cuboid_311_fillet_45_thinner_0"/>
  </body><body name="ground" pos="0 0 0">
    <geom name="ground_geom" type="plane" size="1 1 1"/>
  </body></mujoco>