<mujoco><body name="cylinder_11_fillet_5_normal_2" pos="0 0 0">
    <inertial pos="0 0 0" quat="1 0 0 0" mass="0.04021238596594936" diaginertia="0.000038 0.000038 0.000032"/>
    <freejoint name="cylinder_11_fillet_5_normal_2"/>
    <geom name="cylinder_11_fillet_5_normal_2_geom" type="mesh" mesh="cylinder_11_fillet_5_normal_2"/>
  </body><body name="cuboid_311_fillet_35_thinner_4" pos="0 0 0">
    <inertial pos="0 0 0" quat="1 0 0 0" mass="0.17639999999999995" diaginertia="0.000144 0.001977 0.001977"/>
    <freejoint name="cuboid_311_fillet_35_thinner_4"/>
    <geom name="cuboid_311_fillet_35_thinner_4_geom" type="mesh" mesh="cuboid_311_fillet_35_thinner_4"/>
  </body><body name="cylinder_21_fillet_35_normal_4" pos="0 0 0">
    <inertial pos="0 0 0" quat="1 0 0 0" mass="0.05025815512763243" diaginertia="0.000049 0.000049 0.000074"/>
    <freejoint name="cylinder_21_fillet_35_normal_4"/>
    <geom name="cylinder_21_fillet_35_normal_4_geom" type="mesh" mesh="cylinder_21_fillet_35_normal_4"/>
  </body><body name="cuboid_211_fillet_5_upright_0" pos="0 0 0">
    <inertial pos="0 0 0" quat="0.707 0 0.707 0" mass="0.025000000000000005" diaginertia="0.000010 0.000026 0.000026"/>
    <freejoint name="cuboid_211_fillet_5_upright_0"/>
    <geom name="cuboid_211_fillet_5_upright_0_geom" type="mesh" mesh="cuboid_211_fillet_5_upright_0"/>
  </body><body name="cylinder_21_fillet_35_normal_13" pos="0 0 0">
    <inertial pos="0 0 0" quat="1 0 0 0" mass="0.20282518305343253" diaginertia="0.000505 0.000505 0.000758"/>
    <freejoint name="cylinder_21_fillet_35_normal_13"/>
    <geom name="cylinder_21_fillet_35_normal_13_geom" type="mesh" mesh="cylinder_21_fillet_35_normal_13"/>
  </body><body name="cylinder_21_fillet_15_normal_3" pos="0 0 0">
    <inertial pos="0 0 0" quat="1 0 0 0" mass="0.04097706152474403" diaginertia="0.000035 0.000035 0.000053"/>
    <freejoint name="cylinder_21_fillet_15_normal_3"/>
    <geom name="cylinder_21_fillet_15_normal_3_geom" type="mesh" mesh="cylinder_21_fillet_15_normal_3"/>
  </body><body name="cuboid_211_fillet_5_upright_2" pos="0 0 0">
    <inertial pos="0 0 0" quat="0.707 0 0.707 0" mass="0.03327500000000001" diaginertia="0.000017 0.000042 0.000042"/>
    <freejoint name="cuboid_211_fillet_5_upright_2"/>
    <geom name="cuboid_211_fillet_5_upright_2_geom" type="mesh" mesh="cuboid_211_fillet_5_upright_2"/>
  </body><body name="cuboid_211_fillet_35_upright_4" pos="0 0 0">
    <inertial pos="0 0 0" quat="0.707 0 0.707 0" mass="0.043199999999999995" diaginertia="0.000026 0.000065 0.000065"/>
    <freejoint name="cuboid_211_fillet_35_upright_4"/>
    <geom name="cuboid_211_fillet_35_upright_4_geom" type="mesh" mesh="cuboid_211_fillet_35_upright_4"/>
  </body><body name="cylinder_11_fillet_5_normal_3" pos="0 0 0">
    <inertial pos="0 0 0" quat="1 0 0 0" mass="0.04823326470964581" diaginertia="0.000051 0.000051 0.000044"/>
    <freejoint name="cylinder_11_fillet_5_normal_3"/>
    <geom name="cylinder_11_fillet_5_normal_3_geom" type="mesh" mesh="cylinder_11_fillet_5_normal_3"/>
  </body><body name="cuboid_221_fillet_45_normal_3" pos="0 0 0">
    <inertial pos="0 0 0" quat="0.7071 0.7071 0 0" mass="0.05384453124999999" diaginertia="0.000059 0.000094 0.000059"/>
    <freejoint name="cuboid_221_fillet_45_normal_3"/>
    <geom name="cuboid_221_fillet_45_normal_3_geom" type="mesh" mesh="cuboid_221_fillet_45_normal_3"/>
  </body><body name="cuboid_321_fillet_15_normal_3" pos="0 0 0">
    <inertial pos="0 0 0" quat="0.7071 0.7071 0 0" mass="0.05024414062500001" diaginertia="0.000040 0.000104 0.000080"/>
    <freejoint name="cuboid_321_fillet_15_normal_3"/>
    <geom name="cuboid_321_fillet_15_normal_3_geom" type="mesh" mesh="cuboid_321_fillet_15_normal_3"/>
  </body><body name="cylinder_21_fillet_35_normal_3" pos="0 0 0">
    <inertial pos="0 0 0" quat="1 0 0 0" mass="0.04097706152474403" diaginertia="0.000035 0.000035 0.000053"/>
    <freejoint name="cylinder_21_fillet_35_normal_3"/>
    <geom name="cylinder_21_fillet_35_normal_3_geom" type="mesh" mesh="cylinder_21_fillet_35_normal_3"/>
  </body><body name="cylinder_21_fillet_15_normal_1" pos="0 0 0">
    <inertial pos="0 0 0" quat="1 0 0 0" mass="0.025986947598559216" diaginertia="0.000016 0.000016 0.000025"/>
    <freejoint name="cylinder_21_fillet_15_normal_1"/>
    <geom name="cylinder_21_fillet_15_normal_1_geom" type="mesh" mesh="cylinder_21_fillet_15_normal_1"/>
  </body><body name="cuboid_211_fillet_5_normal_1" pos="0 0 0">
    <inertial pos="0 0 0" quat="1 0 0 0" mass="0.051816796874999994" diaginertia="0.000035 0.000088 0.000088"/>
    <freejoint name="cuboid_211_fillet_5_normal_1"/>
    <geom name="cuboid_211_fillet_5_normal_1_geom" type="mesh" mesh="cuboid_211_fillet_5_normal_1"/>
  </body><body name="cylinder_11_fillet_45_normal_0" pos="0 0 0">
    <inertial pos="0 0 0" quat="1 0 0 0" mass="0.026939157004532463" diaginertia="0.000019 0.000019 0.000017"/>
    <freejoint name="cylinder_11_fillet_45_normal_0"/>
    <geom name="cylinder_11_fillet_45_normal_0_geom" type="mesh" mesh="cylinder_11_fillet_45_normal_0"/>
  </body><body name="ground" pos="0 0 0">
    <geom name="ground_geom" type="plane" size="1 1 1"/>
  </body></mujoco>